{"isAvailable":true,"maps":[{"displayProperties":{"description":"Vex Future, Infinite Forest","name":"The Burnout","icon":"/img/misc/missing_icon_d2.png","hasIcon":false},"originalDisplayProperties":{"description":"Vex Future, Infinite Forest","name":"The Burnout","icon":"/img/misc/missing_icon_d2.png","hasIcon":false},"releaseIcon":"/img/misc/missing_icon_d2.png","releaseTime":0,"completionUnlockHash":0,"activityLightLevel":0,"destinationHash":1782858935,"placeHash":4088006058,"activityTypeHash":4088006058,"tier":-1,"pgcrImage":"/img/destiny_content/pgcr/pvp_the_burnout.jpg","rewards":[],"modifiers":[],"isPlaylist":false,"challenges":[],"optionalUnlockStrings":[],"inheritFromFreeRoam":false,"suppressOtherRewards":false,"playlistItems":[],"matchmaking":{"isMatchmade":false,"minParty":1,"maxParty":3,"maxPlayers":6,"requiresGuardianOath":false},"isPvP":false,"insertionPoints":[],"activityLocationMappings":[],"hash":247771251,"index":357,"redacted":false,"blacklisted":false,"map":"The Burnout","twitterQuery":"trials (Burnout)","activityHash":"247771251","results":39,"destination":{"displayProperties":{"description":"","name":"","hasIcon":false},"placeHash":4088006058,"defaultFreeroamActivityHash":0,"activityGraphEntries":[],"bubbleSettings":[],"bubbles":[],"hash":1782858935,"index":31,"redacted":false,"blacklisted":false}}],"milestone":{"milestoneHash":3842941126,"availableQuests":[{"questItemHash":3565079467}],"order":960}}